moraqib-0.1.0.dist-info/METADATA
moraqib-0.1.0.dist-info/WHEEL
moraqib-0.1.0.dist-info/entry_points.txt
moraqib/__init__.py
moraqib/_client.py
moraqib/_exceptions.py
moraqib/resources/__init__.py
moraqib/resources/_resource.py
moraqib/resources/trace.py
moraqib/types/__init__.py
moraqib/types/common.py
moraqib/types/trace.py
moraqib-0.1.0.dist-info/RECORD
