Metadata-Version: 2.1
Name: moraqib
Version: 0.1.0
Summary: moraqib python sdk
Author-Email: abdelrahman abounida <abdelrahmanaboneda@gmail.com>
License: MIT
Requires-Python: >=3.11
Requires-Dist: httpx>=0.28.1
Requires-Dist: pydantic>=2.10.6
